SimpleDatabaseConnector/Caches.py
SimpleDatabaseConnector/Connectors.py
SimpleDatabaseConnector/__init__.py
SimpleDatabaseConnector-0.0.4.dist-info/LICENSE
SimpleDatabaseConnector-0.0.4.dist-info/METADATA
SimpleDatabaseConnector-0.0.4.dist-info/WHEEL
SimpleDatabaseConnector-0.0.4.dist-info/top_level.txt
SimpleDatabaseConnector-0.0.4.dist-info/RECORD
