Metadata-Version: 2.1
Name: SimpleDatabaseConnector
Version: 0.0.4
Summary: Simple Database Connectors
Home-page: https://github.com/fastskyz/SimplePythonSQLConnector 
Author: fastskyz
Author-email: seppedelanghe17@gmail.com
License: UNKNOWN
Platform: UNKNOWN
Classifier: Development Status :: 2 - Pre-Alpha
Classifier: Programming Language :: Python :: 3
Classifier: License :: OSI Approved :: GNU Affero General Public License v3
Classifier: Operating System :: OS Independent
Requires-Python: >=3.8
Requires-Dist: pyodbc (==4.0.30)
Requires-Dist: uuid (==1.30)
